imagica/__init__.py
imagica/calc.py
imagica/conv.py
imagica/proc.py
imagica-0.1.0.dist-info/LICENSE
imagica-0.1.0.dist-info/WHEEL
imagica-0.1.0.dist-info/METADATA
imagica-0.1.0.dist-info/RECORD
